nerpii/__init__.py
nerpii/faker_generator.py
nerpii/named_entity_recognizer.py
nerpii-0.2.4.dist-info/METADATA
nerpii-0.2.4.dist-info/WHEEL
nerpii-0.2.4.dist-info/RECORD
