Metadata-Version: 2.1
Name: nerpii
Version: 0.2.4
Summary: A python library to perform NER on structured data and generate PII with Faker
Home-page: https://github.com/Clearbox-AI/nerpii
License: GPL
Author: Clearbox AI
Author-email: info@clearbox.ai
Requires-Python: >=3.9,<4.0
Classifier: License :: Other/Proprietary License
Classifier: Programming Language :: Python :: 3
Classifier: Programming Language :: Python :: 3.9
Classifier: Programming Language :: Python :: 3.10
Classifier: Programming Language :: Python :: 3.11
Requires-Dist: faker (>=17.3.0,<18.0.0)
Requires-Dist: gender-guesser (>=0.4.0,<0.5.0)
Requires-Dist: pandas (>=1.5.3,<2.0.0)
Requires-Dist: presidio-analyzer (>=2.2.32,<3.0.0)
Requires-Dist: simple-colors (>=0.1.5,<0.2.0)
Requires-Dist: spacy (>=3.5.0)
Requires-Dist: torch (>=1.13.1)
Requires-Dist: transformers (>=4.26.1,<5.0.0)
Project-URL: Repository, https://github.com/Clearbox-AI/nerpii
